{"cameraMode":{"drawMode":0,"name":"Shaded","section":"Shading Mode"},"sceneLighting":true,"audioPlay":false,"sceneViewState":{"m_AlwaysRefresh":false,"showFog":true,"showSkybox":true,"showFlares":true,"showImageEffects":true,"showParticleSystems":true,"showVisualEffectGraphs":true,"m_FxEnabled":true},"in2DMode":false,"pivot":{"x":825.5230712890625,"y":493.050537109375,"z":18.54296875},"rotation":{"x":0.10854717344045639,"y":0.1843823939561844,"z":0.020494788885116578,"w":-0.9766364693641663},"size":445.5999450683594,"orthographic":false}